lrgasp/__init__.py
lrgasp/data_sets.py
lrgasp/de_novo_rna_data.py
lrgasp/defs.py
lrgasp/entry_metadata.py
lrgasp/entry_validate.py
lrgasp/experiment_metadata.py
lrgasp/expression_data.py
lrgasp/loggingOps.py
lrgasp/metadata_validate.py
lrgasp/model_data.py
lrgasp/objDict.py
lrgasp/read_model_map_data.py
lrgasp/symEnum.py
lrgasp/synapse_access.py
lrgasp/tame_pandas.py
lrgasp/data/encode-metadata.json
lrgasp/data/lrgasp_grch38_sirvs.tsv
lrgasp/data/lrgasp_grcm39_sirvs.tsv
lrgasp/data/simulated-metadata.json
lrgasp_tools-1.12.0.data/scripts/lrgasp-synapse-download
lrgasp_tools-1.12.0.data/scripts/lrgasp-upload-entry
lrgasp_tools-1.12.0.data/scripts/lrgasp-validate-de-novo-rna
lrgasp_tools-1.12.0.data/scripts/lrgasp-validate-entry
lrgasp_tools-1.12.0.data/scripts/lrgasp-validate-entry-metadata
lrgasp_tools-1.12.0.data/scripts/lrgasp-validate-experiment-metadata
lrgasp_tools-1.12.0.data/scripts/lrgasp-validate-expression-matrix
lrgasp_tools-1.12.0.data/scripts/lrgasp-validate-models
lrgasp_tools-1.12.0.data/scripts/lrgasp-validate-read-model-map
lrgasp_tools-1.12.0.dist-info/LICENSE
lrgasp_tools-1.12.0.dist-info/METADATA
lrgasp_tools-1.12.0.dist-info/WHEEL
lrgasp_tools-1.12.0.dist-info/top_level.txt
lrgasp_tools-1.12.0.dist-info/zip-safe
lrgasp_tools-1.12.0.dist-info/RECORD
