Metadata-Version: 2.1
Name: lrgasp-tools
Version: 1.12.0
Summary: LRGASP tools
Home-page: https://github.com/LRGASP/lrgasp-submissions
Author: Mark Diekhans
Author-email: markd@ucsc.edu
License: MIT
Keywords: Bioinformatics,genomics,transcriptomics
Platform: UNKNOWN
Classifier: Development Status :: 4 - Beta
Classifier: Intended Audience :: Developers
Classifier: License :: OSI Approved :: MIT License
Classifier: Natural Language :: English
Classifier: Programming Language :: Python :: 3
Classifier: Programming Language :: Python :: 3.7
Classifier: Programming Language :: Python :: 3.8
Classifier: Programming Language :: Python :: 3.9
Classifier: Operating System :: POSIX
Classifier: Operating System :: MacOS :: MacOS X
Classifier: Topic :: Software Development :: Libraries :: Python Modules
Requires-Python: >=3.7
Requires-Dist: gtfparse (==1.2.1)
Requires-Dist: validators (==0.18.2)
Requires-Dist: synapseclient (==2.4.0)
Requires-Dist: fasta-reader (==1.0.0)
